.gitattributes
.gitignore
.pre-commit-config.yaml
LICENSE
MANIFEST.in
README.md
pyproject.toml
setup.py
.github/dependabot.yml
.github/release-drafter.yml
.github/workflows/codeql.yml
.github/workflows/deploy.yml
.github/workflows/release-drafter.yml
docs/_static/lbr.png
docs/_static/mnt_dark.svg
docs/_static/mnt_light.svg
src/mnt/__init__.py
src/mnt.nanoplacer.egg-info/PKG-INFO
src/mnt.nanoplacer.egg-info/SOURCES.txt
src/mnt.nanoplacer.egg-info/dependency_links.txt
src/mnt.nanoplacer.egg-info/entry_points.txt
src/mnt.nanoplacer.egg-info/requires.txt
src/mnt.nanoplacer.egg-info/top_level.txt
src/mnt/nanoplacer/__init__.py
src/mnt/nanoplacer/main.py
src/mnt/nanoplacer/benchmarks/EPFL/adder.v
src/mnt/nanoplacer/benchmarks/EPFL/arbiter.v
src/mnt/nanoplacer/benchmarks/EPFL/bar.v
src/mnt/nanoplacer/benchmarks/EPFL/cavlc.v
src/mnt/nanoplacer/benchmarks/EPFL/ctrl.v
src/mnt/nanoplacer/benchmarks/EPFL/dec.v
src/mnt/nanoplacer/benchmarks/EPFL/div.v
src/mnt/nanoplacer/benchmarks/EPFL/hyp.v
src/mnt/nanoplacer/benchmarks/EPFL/i2c.v
src/mnt/nanoplacer/benchmarks/EPFL/int2float.v
src/mnt/nanoplacer/benchmarks/EPFL/log2.v
src/mnt/nanoplacer/benchmarks/EPFL/max.v
src/mnt/nanoplacer/benchmarks/EPFL/multiplier.v
src/mnt/nanoplacer/benchmarks/EPFL/priority.v
src/mnt/nanoplacer/benchmarks/EPFL/router.v
src/mnt/nanoplacer/benchmarks/EPFL/sin.v
src/mnt/nanoplacer/benchmarks/EPFL/sqrt.v
src/mnt/nanoplacer/benchmarks/EPFL/square.v
src/mnt/nanoplacer/benchmarks/EPFL/voter.v
src/mnt/nanoplacer/benchmarks/ISCAS85/c1355.v
src/mnt/nanoplacer/benchmarks/ISCAS85/c17.v
src/mnt/nanoplacer/benchmarks/ISCAS85/c1908.v
src/mnt/nanoplacer/benchmarks/ISCAS85/c2670.v
src/mnt/nanoplacer/benchmarks/ISCAS85/c3540.v
src/mnt/nanoplacer/benchmarks/ISCAS85/c432.v
src/mnt/nanoplacer/benchmarks/ISCAS85/c499.v
src/mnt/nanoplacer/benchmarks/ISCAS85/c5315.v
src/mnt/nanoplacer/benchmarks/ISCAS85/c6288.v
src/mnt/nanoplacer/benchmarks/ISCAS85/c7552.v
src/mnt/nanoplacer/benchmarks/ISCAS85/c880.v
src/mnt/nanoplacer/benchmarks/TOY/1bitAdderAOIG.v
src/mnt/nanoplacer/benchmarks/TOY/1bitAdderMaj.v
src/mnt/nanoplacer/benchmarks/TOY/FA.v
src/mnt/nanoplacer/benchmarks/TOY/FS.v
src/mnt/nanoplacer/benchmarks/TOY/HA.v
src/mnt/nanoplacer/benchmarks/TOY/HS.v
