Metadata-Version: 2.4
Name: mnt.nanoplacer
Version: 0.2.5
Summary: NanoPlaceR - An open-source framework for placement and routing of Field-coupled Nanotechnologies based on reinforcement learning.
Author-email: Simon Hofmann <simon.t.hofmann@tum.de>
License: MIT License
Project-URL: Homepage, https://github.com/cda-tum/NanoPlaceR
Project-URL: Bug Tracker, https://github.com/cda-tum/NanoPlaceR/issues
Project-URL: Discussions, https://github.com/cda-tum/NanoPlaceR/discussions
Project-URL: Research, https://www.cda.cit.tum.de/research/fcn/
Keywords: FCN,physical design
Classifier: Development Status :: 4 - Beta
Classifier: Intended Audience :: Developers
Classifier: License :: OSI Approved :: MIT License
Classifier: Operating System :: Microsoft :: Windows
Classifier: Operating System :: MacOS
Classifier: Operating System :: POSIX :: Linux
Classifier: Programming Language :: Python :: 3 :: Only
Classifier: Programming Language :: Python :: 3.8
Classifier: Programming Language :: Python :: 3.9
Classifier: Programming Language :: Python :: 3.10
Classifier: Programming Language :: Python :: 3.11
Classifier: Programming Language :: Python :: 3.12
Classifier: Intended Audience :: Science/Research
Classifier: Natural Language :: English
Classifier: Topic :: Scientific/Engineering :: Electronic Design Automation (EDA)
Requires-Python: <3.13
License-File: LICENSE
Requires-Dist: networkx>=3.2.1
Requires-Dist: numpy>=1.26.3
Requires-Dist: pre-commit>=3.6.0
Requires-Dist: setuptools>=68.2.0
Requires-Dist: sb3_contrib>=2.2.1
Requires-Dist: tensorboard>=2.15.1
Requires-Dist: wheel>=0.38.0
Requires-Dist: mnt.pyfiction>=0.6.1
Provides-Extra: test
Requires-Dist: pytest>=8.2.1; extra == "test"
Provides-Extra: coverage
Requires-Dist: mnt.nanoplacer[test]; extra == "coverage"
Requires-Dist: pytest-cov[toml]; extra == "coverage"
Dynamic: license-file
